Metadata-Version: 2.1
Name: bit-JCO
Version: 0.8.1
Summary: Bitcoin made easy.
Home-page: https://github.com/RastinS/tron-api-JCO
Download-URL: https://github.com/RastinS/tron-api-JCO
Author: Rustin Soraki
Author-email: rustin.souraki@gmail.com
Maintainer: Rustin Soraki
Maintainer-email: rustin.souraki@gmail.com
License: MIT
Keywords: bitcoin,cryptocurrency,payments,tools,wallet
Classifier: Development Status :: 4 - Beta
Classifier: Intended Audience :: Developers
Classifier: Intended Audience :: End Users/Desktop
Classifier: License :: OSI Approved :: MIT License
Classifier: Natural Language :: English
Classifier: Operating System :: OS Independent
Classifier: Programming Language :: Python :: 3.5
Classifier: Programming Language :: Python :: 3.6
Classifier: Programming Language :: Python :: 3.7
Classifier: Programming Language :: Python :: Implementation :: CPython
Classifier: Programming Language :: Python :: Implementation :: PyPy
License-File: LICENSE.txt
License-File: AUTHORS.rst
Requires-Dist: coincurve (>=4.3.0)
Requires-Dist: requests
Provides-Extra: cache
Requires-Dist: lmdb ; extra == 'cache'
Provides-Extra: cli
Requires-Dist: appdirs ; extra == 'cli'
Requires-Dist: click ; extra == 'cli'
Requires-Dist: privy ; extra == 'cli'
Requires-Dist: tinydb ; extra == 'cli'
